<!-- --- IFF010 --- --><?xml version="1.0"?><ServicoCadastro>  <nome>Receber bolsa de Pesquisa</nome>  <sigla/>  <descricao> Alunos de graduação e pós-graduação que participam de projetos de pesquisa na Universidade podem concorrer a auxílio financeiro em função destas atividades, através deste serviço.</descricao>  <contato/>  <gratuito>false</gratuito>  <servicoDigital>true</servicoDigital>  <linkServicoDigital>www.iff.edu.br</linkServicoDigital>  <solicitantes>    <id>1</id>    <tipo>Cidadãos e Famílias</tipo>    </requisitos>    <id>1</id>    <tipo>Empresas privadas</tipo>    </requisitos>    <id>1</id>    <tipo>Empresas públicas ou de economia mista</tipo>    </requisitos>    <id>1</id>    <tipo>Pessoas jurídicas de direito privado sem fins lucrativos</tipo>    </requisitos>    <id>1</id>    <tipo>Órgãos da administração direta</tipo>    </requisitos>    <id>1</id>    <tipo>Estados e municípios</tipo>    </requisitos>  </solicitantes>  <tempoTotalEstimado>    <entre>      <min>2</min>      <max>7</max>      <unidade>dias</unidade>    </entre>  </tempoTotalEstimado>  <segmentosDaSociedade>    <item>      <item>Cidadãos</item>      <idSegmento>1</idSegmento>      <idServicoSegmento>1</idServicoSegmento>    </item>    <item>      <item>Órgãos e entidades públicas</item>      <idSegmento>2</idSegmento>      <idServicoSegmento>1</idServicoSegmento>    </item>    <item>      <item>Empresas</item>      <idSegmento>3</idSegmento>      <idServicoSegmento>1</idServicoSegmento>    </item>    <item>      <item>Demais segmentos (ONGs, organizações sociais, etc)</item>      <idSegmento>4</idSegmento>      <idServicoSegmento>1</idServicoSegmento>    </item>  </segmentosDaSociedade>  <areasDeInteresse>    <item>Pesquisa, Ciência, Inovação e Tecnologia</item>  </areasDeInteresse>  <etapas>    <id>1</id>    <titulo>Solicitar e enviar informações e dados via email.</titulo>    <descricao>Solicitar e enviar informações e dados via email.</descricao>    <documentos>      <caso/>    </documentos>    <custos>      <custos/>      <caso/>    </custos>    <canaisDePrestacao>      <canaisDePrestacao>        <id>1</id>        <tipo>web</tipo>        <descricao>www.iff.edu.br</descricao>      </canaisDePrestacao>      <caso/>      <canaisDePrestacao>        <id>1</id>        <tipo>e-mail</tipo>        <descricao>propei@iff.edu.br</descricao>      </canaisDePrestacao>      <caso/>      <canaisDePrestacao>        <id>1</id>        <tipo>telefone</tipo>        <descricao>2227375615</descricao>      </canaisDePrestacao>      <caso/>      <canaisDePrestacao>        <id>1</id>        <tipo>aplicativo-movel</tipo>        <descricao>WhatsApp e SUAP</descricao>      </canaisDePrestacao>      <caso/>      <canaisDePrestacao>        <id>1</id>        <tipo>postal</tipo>        <descricao>Rua Coronel Walter Kramer, 357 - Parque Santo Antônio - Campos dos Goytacazes, RJ - CEP 28080-565</descricao>      </canaisDePrestacao>      <caso/>      <canaisDePrestacao>        <id>1</id>        <tipo>presencial</tipo>        <descricao>Reitoria</descricao>      </canaisDePrestacao>      <caso/>    </canaisDePrestacao>  </etapas>  <palavrasChave/>  <legislacoes/>  <validadeDocumento/><!--  <servicosRelacionados>--><!--    <id></id>--><!--    <nome>Atualização do currículo na plataforma Lattes  e busca/atualização de informações na plataforma Carlos Chagas, ambas do CNPq.</nome>--><!--  </servicosRelacionados>--><servicosRelacionados/></ServicoCadastro>
