<!-- --- UFPA007 --- --><?xml version="1.0"?><ServicoCadastro>  <nome>Registrar diplomas de faculdades, centros universitários e universidades privadas</nome>  <sigla/>  <nomesPopulares>    <item>Registro de Diplomas de IES externas</item>    <id>1</id>  </nomesPopulares>  <descricao> Instituições privadas de Educação Superior precisam registrar seus diplomas de graduação e pós-graduação junto a Instituições Federais de Ensino Superior para que estes tenham validade. Para registrar diplomas nesta instituição, siga as orientações abaixo.</descricao>  <contato/>  <gratuito>false</gratuito>  <servicoDigital>false</servicoDigital>  <solicitantes>    <id>1</id>    <tipo>Empresas privadas</tipo>    </requisitos>  </solicitantes>  <tempoTotalEstimado>    <entre>      <min>60</min>      <max>90</max>      <unidade>dias</unidade>    </entre>  </tempoTotalEstimado>  <segmentosDaSociedade>    <item>      <item>Cidadãos</item>      <idSegmento>1</idSegmento>      <idServicoSegmento>1</idServicoSegmento>    </item>    <item>      <item>Órgãos e entidades públicas</item>      <idSegmento>2</idSegmento>      <idServicoSegmento>1</idServicoSegmento>    </item>    <item>      <item>Empresas</item>      <idSegmento>3</idSegmento>      <idServicoSegmento>1</idServicoSegmento>    </item>    <item>      <item>Demais segmentos (ONGs, organizações sociais, etc)</item>      <idSegmento>4</idSegmento>      <idServicoSegmento>1</idServicoSegmento>    </item>  </segmentosDaSociedade>  <areasDeInteresse>    <item>Administração</item>  </areasDeInteresse>  <etapas>    <id>1</id>    <titulo>Protocar os diplomas para registro</titulo>    <descricao>Protocar os diplomas para registro</descricao>    <documentos>      <caso/>    </documentos>    <custos>      <custos/>      <caso/>    </custos>    <canaisDePrestacao>      <canaisDePrestacao>        <id>1</id>        <tipo>presencial</tipo>        <descricao>CENTRO DE REGISTRO E INDICADORES ACADÊMICOS</descricao>      </canaisDePrestacao>      <caso/>    </canaisDePrestacao>    <id>1</id>    <titulo>Recebimentos dos diplomas registrados</titulo>    <descricao>Recebimentos dos diplomas registrados</descricao>    <documentos>      <caso/>    </documentos>    <custos>      <custos/>      <caso/>    </custos>    <canaisDePrestacao>      <canaisDePrestacao>        <id>1</id>        <tipo>presencial</tipo>        <descricao>Centro de Registro e Indicadores Acadêmicos</descricao>      </canaisDePrestacao>      <caso/>    </canaisDePrestacao>  </etapas>  <palavrasChave/>  <legislacoes/>  <validadeDocumento/><servicosRelacionados/></ServicoCadastro>
